rexilion/__init__.py
rexilion/backtest/__init__.py
rexilion/backtest/diagram.py
rexilion/backtest/entryexitlogic.py
rexilion/backtest/entryexitlogic_numba.py
rexilion/backtest/formula.py
rexilion/backtest/formula_numba.py
rexilion/backtest/model.py
rexilion/backtest/util.py
rexilion_backtest-0.0.1a30.dist-info/METADATA
rexilion_backtest-0.0.1a30.dist-info/WHEEL
rexilion_backtest-0.0.1a30.dist-info/top_level.txt
rexilion_backtest-0.0.1a30.dist-info/RECORD
