Metadata-Version: 2.4
Name: rexilion-backtest
Version: 0.0.1a30
Summary: Backtest Engine
Author: Rexilion Technologies
Author-email: fkh714@gmail.com
Requires-Python: >=3.12
Requires-Dist: matplotlib
Requires-Dist: seaborn
Requires-Dist: pandas
Requires-Dist: numpy
Requires-Dist: scipy
Requires-Dist: numba
Dynamic: author
Dynamic: author-email
Dynamic: requires-dist
Dynamic: requires-python
Dynamic: summary
